LICENSE
MANIFEST.in
README.md
setup.py
blobstash/base/__init__.py
blobstash/base/blobstore.py
blobstash/base/client.py
blobstash/base/error.py
blobstash/base/iterator.py
blobstash/base/kvstore.py
blobstash/base/test_utils.py
blobstash_base.egg-info/PKG-INFO
blobstash_base.egg-info/SOURCES.txt
blobstash_base.egg-info/dependency_links.txt
blobstash_base.egg-info/requires.txt
blobstash_base.egg-info/top_level.txt