Metadata-Version: 1.2
Name: blobstash-base
Version: 0.0.5
Summary: BlobStash client
Home-page: https://github.com/tsileo/blobstash-python-base
Author: Thomas Sileo
Author-email: t@a4.io
License: MIT
Keywords: blobstash client
Platform: UNKNOWN
Classifier: Development Status :: 3 - Alpha
Classifier: Intended Audience :: Developers
Classifier: License :: OSI Approved :: MIT License
Classifier: Programming Language :: Python :: 3
Classifier: Programming Language :: Python :: 3.6
Requires-Python: >=3.6
